nbt/__init__.py
nbt/chunk.py
nbt/nbt.py
nbt/region.py
nbt/world.py
NBT-1.5.1.dist-info/LICENSE.txt
NBT-1.5.1.dist-info/METADATA
NBT-1.5.1.dist-info/WHEEL
NBT-1.5.1.dist-info/top_level.txt
NBT-1.5.1.dist-info/RECORD
