Metadata-Version: 2.1
Name: NBT
Version: 1.5.1
Summary: Named Binary Tag Reader/Writer
Home-page: http://github.com/twoolie/NBT
Author: Thomas Woolford
Author-email: woolford.thomas@gmail.com
License:  Copyright (c) 2010-2013 Thomas Woolford and contributors
Platform: UNKNOWN
Classifier: Development Status :: 5 - Production/Stable
Classifier: Intended Audience :: Developers
Classifier: License :: OSI Approved :: MIT License
Classifier: Operating System :: OS Independent
Classifier: Programming Language :: Python
Classifier: Programming Language :: Python :: 2.7
Classifier: Programming Language :: Python :: 3.3
Classifier: Programming Language :: Python :: 3.4
Classifier: Programming Language :: Python :: 3.5
Classifier: Programming Language :: Python :: 3.6
Classifier: Topic :: Games/Entertainment
Classifier: Topic :: Software Development :: Libraries :: Python Modules
License-File: LICENSE.txt
